line_decoder/1to2_line_decoder.v
/*
 * 	LINE DECODER
 *
 * A decoder is a circuit that changes a code into a set of signals. 
 * Lets begin to study and design a line decoder which is a common type of decoder wit n-digit binary number and 2^n data lines.
 *
 * Truth table:
 * A	| D1	| D0
 * ---	| ---	| ---
 * 0	| 0	| 1
 * 1	| 1	| 0
 *
 * 'A' is the address and 'D' is the dataline. D0 is 'NOT A' and D1 is 'A'.
 *
 * Written by: DraKo
 * Date created: 01-05-2021
 */
 
 module line_decoder();
 	reg a = 0;
 	wire d0, d1;
 	
 	assign d0 = ~a;
 	assign d1 = a;
 	
 	always
 		#10 a = ~a;
 	
 	initial begin
 		#10
 		$monitor("a=%b, d1=%b, d0=%b", a, d1,d0);
 		$dumpfile("1to2linedecoder.vcd");
 		$dumpvars(0, line_decoder);
 	#110 $finish;
 	
 	end
 	
 endmodule

line_decoder/1to2linedecoder.vcd
$date
	Sat May  1 16:59:12 2021
$end
$version
	Icarus Verilog
$end
$timescale
	1s
$end
$scope module line_decoder $end
$var wire 1 ! d0 $end
$var wire 1 " d1 $end
$var reg 1 # a $end
$upscope $end
$enddefinitions $end
#10
$dumpvars
1#
1"
0!
$end
#20
1!
0"
0#
#30
0!
1"
1#
#40
1!
0"
0#
#50
0!
1"
1#
#60
1!
0"
0#
#70
0!
1"
1#
#80
1!
0"
0#
#90
0!
1"
1#
#100
1!
0"
0#
#110
0!
1"
1#
#120
1!
0"
0#
