functions.v
module logic_function ();
	reg a = 0, b = 0;
	wire f;

	assign f = a & ~b | ~a & b;
	
	always
		#10 a = ~a;

	always
		#20 b = ~b;

	initial begin
		$monitor("a=%b, b=%b, f=%b", a,b,f);
		$dumpfile("functions.vcd");
		$dumpvars(0, logic_function);

		#100 $finish;
	end
endmodule

functions.vcd
$date
	Mon Mar 29 17:29:12 2021
$end
$version
	Icarus Verilog
$end
$timescale
	1s
$end
$scope module logic_function $end
$var wire 1 ! f $end
$var reg 1 " a $end
$var reg 1 # b $end
$upscope $end
$enddefinitions $end
#0
$dumpvars
0#
0"
0!
$end
#10
1!
1"
#20
1!
0"
1#
#30
0!
1"
#40
0"
0#
#50
1!
1"
#60
1!
0"
1#
#70
0!
1"
#80
0"
0#
#90
1!
1"
#100
1!
0"
1#
