inverter/inverter.v
// Module initialization
module inverter(
  input   a,      // input declaration
  output  y       // output declaration
);
  assign y = ~a;  // Assigning output value
endmodule

inverter.vcd
$date
	Mon Mar 29 17:34:47 2021
$end
$version
	Icarus Verilog
$end
$timescale
	1s
$end
$scope module inverter $end
$var wire 1 ! y $end
$var reg 1 " a $end
$upscope $end
$enddefinitions $end
#0
$dumpvars
0"
1!
$end
#10
0!
1"
#20
1!
0"
#30
0!
1"
#40
1!
0"
#50
0!
1"
#60
1!
0"
#70
0!
1"
#80
1!
0"
#90
0!
1"
#100
1!
0"
