siso/siso.v
// 4-bit Single Input Single Output (SISO)

module siso(
	input 	i_clk,
	input 	i_d,
	input 	i_rst,
	output 	o_siso,
	output 	r_d0,
	output 	r_d1,
	output 	r_d2
);

	reg r_d3;
	reg r_d2;
	reg r_d1;
	reg r_d0;

	initial begin
		r_d2	<= 1'b0;
		r_d1	<= 1'b0;
		r_d0	<= 1'b0;
	end

	always @(posedge i_clk) begin
		if(!i_rst) begin
			r_d2	<= 1'b0;
			r_d1	<= 1'b0;
			r_d0	<= 1'b0;
		end

		else begin
			r_d0 	<= i_d;
			r_d1 	<= r_d0;
			r_d2 	<= r_d1;
			r_d3 	<= r_d2;
		end
	end

	assign o_siso = r_d3;

endmodule

siso/tb_siso.v
// SISO TESTBENCH

`include "siso.v"

module tb_siso();
	
	parameter PERIOD 	= 10;
	parameter HP 			= PERIOD/2;
	parameter LEN 		= 4;		// Adjust this based on the length of the pattern

	reg 	i_clk;
	reg 	i_d;
	reg 	i_rst;
	wire 	o_siso;
	integer i;
	reg [LEN-1:0] pattern = 1101;		// Modify pattern here
	wire r_d0;
	wire r_d1;
	wire r_d2;

	always #HP i_clk <= ~i_clk;

	initial begin
		i_clk = 1'b1;
		i_d 	= 1'b0;
		i_rst = 1'b0;
		i_rst = 1'b1;

		for(i=0; i<LEN; i=i+1) 
			#PERIOD i_d = pattern[i];
		#PERIOD i_d = 1'b0;
	end

	/*/
	initial begin
		$display("time\td\to_siso");
		$monitor("%0t\t",$time,i_d,"\t",o_siso);
		#(2*LEN*PERIOD) $finish;
	end
	/*/

	initial begin
		$display("time\td\td0\td1\td2\to_siso");
		$monitor("%0t\t%b\t%b\t%b\t%b\t%b",$time,i_d,r_d0,r_d1,r_d2,o_siso);
		#(40+(LEN*PERIOD)) $finish;
	end

	initial begin
		$dumpfile("tb_siso.vcd");
		$dumpvars(0,tb_siso);
	end

	siso SISO(
		.i_clk(i_clk),
		.i_d(i_d),
		.i_rst(i_rst),
		.o_siso(o_siso),
		.r_d0(r_d0),
		.r_d1(r_d1),
		.r_d2(r_d2)
	);	
endmodule

siso/tb_siso.vcd
$date
	Sun Nov 28 13:48:48 2021
$end
$version
	Icarus Verilog
$end
$timescale
	1s
$end
$scope module tb_siso $end
$var wire 1 ! r_d2 $end
$var wire 1 " r_d1 $end
$var wire 1 # r_d0 $end
$var wire 1 $ o_siso $end
$var reg 1 % i_clk $end
$var reg 1 & i_d $end
$var reg 1 ' i_rst $end
$var reg 4 ( pattern [3:0] $end
$var integer 32 ) i [31:0] $end
$scope module SISO $end
$var wire 1 % i_clk $end
$var wire 1 & i_d $end
$var wire 1 ' i_rst $end
$var wire 1 $ o_siso $end
$var reg 1 # r_d0 $end
$var reg 1 " r_d1 $end
$var reg 1 ! r_d2 $end
$var reg 1 * r_d3 $end
$upscope $end
$upscope $end
$enddefinitions $end
#0
$dumpvars
x*
b0 )
b1101 (
1'
0&
1%
x$
0#
x"
x!
$end
#5
0%
#10
0"
1#
1%
b1 )
1&
#15
0%
#20
0!
1"
0#
1%
b10 )
0&
#25
0%
#30
0$
0*
1!
0"
1#
1%
b11 )
1&
#35
0%
#40
1$
1*
0!
1"
1%
b100 )
#45
0%
#50
0$
0*
1!
0#
1%
0&
#55
0%
#60
1$
1*
0"
1%
#65
0%
#70
0!
1%
#75
0%
#80
0$
0*
1%
