t_flipflop/tff.v
////////////////////////////////////////
//
// T FLIP FLOP
//
// Port		| Type
// =======|=====
// clk		| input
// i_t		| input
// o_q		| output
// o_qbar	| output
//
// Truth Table
// Clock	| T	| Q	| Q'
// =======|=======|===
// 0			| 0	| 0	| 1
// 1			| 0	| 0	| 1
// 0			| 1	| 0	| 1
// 1			| 1	| 1	| 0
// 0			| 0	| 1	| 0
// 1			| 0	| 1	| 0
////////////////////////////////////////

module tff(
	input 	clk,
	input 	i_t,
	output	o_q,
	output	o_qbar
);
	reg	o_q = 1'b0;
	reg	o_qn = 1'b0;

	always@(posedge clk) begin
		if(!i_t)
			o_q <= o_q ;
		else
			o_q <= ~o_q;
	end

	assign o_qbar = ~o_q;
endmodule

t_flipflop/tb_tff.v
////////////////////////////////////////
// TESTBENCH
////////////////////////////////////////

`include "tff.v"

module tb_tff();

	parameter PERIOD = 10;
	parameter HP = PERIOD/2;

	reg 	clk;
	reg 	i_t;
	wire 	o_q;
	wire 	o_qbar;

	reg [1:0] i 	= 1'b0;

	always #HP clk++;

	initial begin 
		clk = 1'b0;
		i_t = 1'b0;
		for (i=0; i<4; i=i+1)
			#HP i_t = i[1];
	end

	tff TFLIPFLOP(
		.clk(clk),
		.i_t(i_t),
		.o_q(o_q),
		.o_qbar(o_qbar)
	);

	initial begin
		$dumpfile("tb_tff.vcd");
		$dumpvars(0,tb_tff);
	end

	initial begin
		$display("clk\ti_t\to_q\to_qbar");
		$monitor(clk,"\t",i_t,"\t",o_q,"\t",o_qbar);
		#40 $finish;
	end

endmodule

designs/t_flipflop/tb_tff.vcd
$date
	Sat Nov 27 19:14:20 2021
$end
$version
	Icarus Verilog
$end
$timescale
	1s
$end
$scope module tb_tff $end
$var wire 1 ! o_qbar $end
$var wire 1 " o_q $end
$var reg 1 # clk $end
$var reg 2 $ i [1:0] $end
$var reg 1 % i_t $end
$scope module TFLIPFLOP $end
$var wire 1 # clk $end
$var wire 1 % i_t $end
$var wire 1 ! o_qbar $end
$var reg 1 " o_q $end
$var reg 1 & o_qn $end
$upscope $end
$upscope $end
$enddefinitions $end
#0
$dumpvars
0&
0%
b0 $
0#
0"
1!
$end
#5
b1 $
1#
#10
b10 $
0#
#15
0!
1"
b11 $
1%
1#
#20
b0 $
0#
#25
b1 $
0%
1#
#30
b10 $
0#
#35
1!
0"
b11 $
1%
1#
#40
b0 $
0#
