inverter/inverter.v
module inverter();
	wire y;
	reg a = 0;
	
	assign y=~a;
	
	always
		#10 a = ~a;

	initial begin
		$monitor("a=%b, y=%b", a, y);
		$dumpfile("inverter.vcd");
		$dumpvars(0, inverter);
	#100 $finish;
	end
endmodule

inverter/inverter.vcd
$date
	Tue Apr  6 10:56:35 2021
$end
$version
	Icarus Verilog
$end
$timescale
	1s
$end
$scope module inverter $end
$var wire 1 ! y $end
$var reg 1 " a $end
$upscope $end
$enddefinitions $end
#0
$dumpvars
0"
1!
$end
#10
0!
1"
#20
1!
0"
#30
0!
1"
#40
1!
0"
#50
0!
1"
#60
1!
0"
#70
0!
1"
#80
1!
0"
#90
0!
1"
#100
1!
0"
